{
	"configurations" : 
	[
		{
			"directories" : 
			[
				{
					"build" : ".",
					"minimumCMakeVersion" : 
					{
						"string" : "3.17"
					},
					"projectIndex" : 0,
					"source" : ".",
					"targetIndexes" : 
					[
						0
					]
				}
			],
			"name" : "Debug",
			"projects" : 
			[
				{
					"directoryIndexes" : 
					[
						0
					],
					"name" : "LinerAlgebra",
					"targetIndexes" : 
					[
						0
					]
				}
			],
			"targets" : 
			[
				{
					"directoryIndex" : 0,
					"id" : "LinerAlgebra::@6890427a1f51a3e7e1df",
					"jsonFile" : "target-LinerAlgebra-Debug-3e003ca45f5a1962af84.json",
					"name" : "LinerAlgebra",
					"projectIndex" : 0
				}
			]
		}
	],
	"kind" : "codemodel",
	"paths" : 
	{
		"build" : "D:/C++_Code/Algorithm/LinerAlgebra/out/build/x64-Debug",
		"source" : "D:/C++_Code/Algorithm/LinerAlgebra"
	},
	"version" : 
	{
		"major" : 2,
		"minor" : 2
	}
}
